alphapept/__init__.py
alphapept/__main__.py
alphapept/__version__.py
alphapept/_modidx.py
alphapept/_nbdev.py
alphapept/additional_code.py
alphapept/amino_acids.tsv
alphapept/ap_round.png
alphapept/chem.py
alphapept/clr_utils.py
alphapept/constants.py
alphapept/contaminants.fasta
alphapept/contributing.py
alphapept/custom_plots.yaml
alphapept/display.py
alphapept/export.py
alphapept/fasta.py
alphapept/favicon.ico
alphapept/feature_finding.py
alphapept/file_formats.py
alphapept/interface.py
alphapept/io.py
alphapept/label.py
alphapept/matching.py
alphapept/modifications.tsv
alphapept/paths.py
alphapept/performance.py
alphapept/pyrawfilereader.py
alphapept/quantification.py
alphapept/recalibration.py
alphapept/score.py
alphapept/search.py
alphapept/settings.py
alphapept/stylesheets.py
alphapept/test.py
alphapept/utils.py
alphapept/webui.py
alphapept/__pycache__/__init__.cpython-38.pyc
alphapept/ext/__init__.py
alphapept/ext/bruker/__init__.py
alphapept/ext/bruker/libtimsdata.so
alphapept/ext/bruker/timsdata.dll
alphapept/ext/bruker/timsdata.lib
alphapept/ext/bruker/timsdata.py
alphapept/ext/bruker/tsfdata.py
alphapept/ext/bruker/FF/THIRD-PARTY-LICENSE-README.txt
alphapept/ext/bruker/FF/proteomics_4d.config
alphapept/ext/bruker/FF/linux64/libtbb.so.2
alphapept/ext/bruker/FF/linux64/uff-cmdline2
alphapept/ext/bruker/FF/win64/tbb.dll
alphapept/ext/bruker/FF/win64/uff-cmdline2.exe
alphapept/ext/thermo_fisher/THERMO_LICENSE.txt
alphapept/ext/thermo_fisher/ThermoFisher.CommonCore.Data.dll
alphapept/ext/thermo_fisher/ThermoFisher.CommonCore.RawFileReader.dll
alphapept/gui/__init__.py
alphapept/gui/constants.py
alphapept/gui/experiment.py
alphapept/gui/fasta.py
alphapept/gui/filewatcher.py
alphapept/gui/history.py
alphapept/gui/results.py
alphapept/gui/start.py
alphapept/gui/status.py
alphapept/gui/utils.py
alphapept/img/logo.ico
alphapept-0.5.3.dist-info/LICENSE
alphapept-0.5.3.dist-info/METADATA
alphapept-0.5.3.dist-info/WHEEL
alphapept-0.5.3.dist-info/entry_points.txt
alphapept-0.5.3.dist-info/top_level.txt
alphapept-0.5.3.dist-info/RECORD
