Metadata-Version: 2.1
Name: alphapept
Version: 0.5.3
Summary: A modular, python-based framework for mass spectrometry.
Home-page: https://github.com/mannlabs/alphapept
Author: Maximilian T. Strauss
Author-email: straussmaximilian@gmail.com
License: MIT License
Keywords: MS,mass spectrometry,python,numba
Classifier: Development Status :: 3 - Alpha
Classifier: Intended Audience :: Developers
Classifier: Natural Language :: English
Classifier: Programming Language :: Python :: 3.6
Classifier: Programming Language :: Python :: 3.7
Classifier: Programming Language :: Python :: 3.8
Classifier: Programming Language :: Python :: 3.9
Classifier: Programming Language :: Python :: 3.10
Classifier: License :: OSI Approved :: MIT License
Requires-Python: >=3.6
License-File: LICENSE
Requires-Dist: biopython
Requires-Dist: click
Requires-Dist: fastcore
Requires-Dist: h5py
Requires-Dist: matplotlib
Requires-Dist: networkx
Requires-Dist: numba
Requires-Dist: numpy
Requires-Dist: pandas
Requires-Dist: psutil
Requires-Dist: pyteomics
Requires-Dist: pyyaml
Requires-Dist: scikit-learn
Requires-Dist: scipy
Requires-Dist: SQLAlchemy
Requires-Dist: tables
Requires-Dist: tqdm
Requires-Dist: alphatims
Requires-Dist: alpharaw
Requires-Dist: pywin32 >=305 ; sys_platform == "win32"
Requires-Dist: pythonnet >=2.5.2 ; sys_platform == "win32"
Requires-Dist: tables ==3.6.1 ; sys_platform == "win32"
Provides-Extra: develop
Requires-Dist: bumpversion ; extra == 'develop'
Requires-Dist: jupyter-contrib-nbextensions ; extra == 'develop'
Requires-Dist: jupyter ; extra == 'develop'
Requires-Dist: nbdev ; extra == 'develop'
Requires-Dist: pyinstaller ; extra == 'develop'
Requires-Dist: twine ; extra == 'develop'
Requires-Dist: wget ; extra == 'develop'
Provides-Extra: develop-stable
Requires-Dist: bumpversion >=0.6.0 ; extra == 'develop-stable'
Requires-Dist: jupyter-contrib-nbextensions >=0.5.1 ; extra == 'develop-stable'
Requires-Dist: jupyter >=1.0.0 ; extra == 'develop-stable'
Requires-Dist: nbdev >=2.0.0 ; extra == 'develop-stable'
Requires-Dist: pyinstaller ==5.2 ; extra == 'develop-stable'
Requires-Dist: twine >=3.4.1 ; extra == 'develop-stable'
Requires-Dist: wget ==3.2 ; extra == 'develop-stable'
Provides-Extra: gui
Requires-Dist: plotly-express ; extra == 'gui'
Requires-Dist: streamlit ; extra == 'gui'
Requires-Dist: watchdog ; extra == 'gui'
Requires-Dist: wget ; extra == 'gui'
Provides-Extra: gui-stable
Requires-Dist: plotly-express ==0.4.1 ; extra == 'gui-stable'
Requires-Dist: streamlit >=1.23.0 ; extra == 'gui-stable'
Requires-Dist: watchdog ==2.1.9 ; extra == 'gui-stable'
Requires-Dist: wget ==3.2 ; extra == 'gui-stable'
Provides-Extra: legacy
Requires-Dist: python-lzf ; extra == 'legacy'
Provides-Extra: legacy-stable
Requires-Dist: python-lzf ==0.2.4 ; extra == 'legacy-stable'
Provides-Extra: stable
Requires-Dist: biopython ==1.79 ; extra == 'stable'
Requires-Dist: click >=7.1.2 ; extra == 'stable'
Requires-Dist: fastcore ==1.5.26 ; extra == 'stable'
Requires-Dist: h5py ==3.7.0 ; extra == 'stable'
Requires-Dist: matplotlib ==3.6.1 ; extra == 'stable'
Requires-Dist: networkx ==2.8.6 ; extra == 'stable'
Requires-Dist: numba ==0.55.2 ; extra == 'stable'
Requires-Dist: numpy ==1.20.3 ; extra == 'stable'
Requires-Dist: pandas ==2.0.1 ; extra == 'stable'
Requires-Dist: psutil ==5.9.1 ; extra == 'stable'
Requires-Dist: pyteomics ==4.5.5 ; extra == 'stable'
Requires-Dist: pyyaml ==6.0 ; extra == 'stable'
Requires-Dist: scikit-learn ==1.1.2 ; extra == 'stable'
Requires-Dist: scipy ==1.8.1 ; extra == 'stable'
Requires-Dist: SQLAlchemy ==1.4.39 ; extra == 'stable'
Requires-Dist: tables ==3.6.1 ; extra == 'stable'
Requires-Dist: tqdm ==4.64.0 ; extra == 'stable'
Requires-Dist: alphatims ==1.0.7 ; extra == 'stable'
Requires-Dist: alpharaw ==0.1.0 ; extra == 'stable'
